bardToken
