Metadata-Version: 2.1
Name: bardToken
Version: 0.0.3
Summary: auto login google account by selenium chrome driver 
Home-page: https://pypi.org/project/bardToken
Author: KuoYuan Li
Author-email: funny4875@gmail.com
License: UNKNOWN
Keywords: bardToken,auto bard token,bard api,selenium,google auth,chromedriver
Platform: UNKNOWN
Classifier: License :: OSI Approved :: MIT License
Classifier: Programming Language :: Python :: 3
